xiaoranli_quiz/__init__.py
xiaoranli_quiz/main.py
xiaoranli_quiz/manipulation_data.py
xiaoranli_quiz/my_structure.py
xiaoranli_quiz/questions.py
xiaoranli_quiz/summary.py
xiaoranli_quiz/data/answer_python.ipynb
xiaoranli_quiz/data/english_quiz.json
xiaoranli_quiz/data/leetcode_quizz.ipynb
xiaoranli_quiz/data/python_quizz.ipynb
xiaoranli_quiz/data/torch_quizz.ipynb
xiaoranli_quiz/data/word_quizz.json
xiaoranli_quiz-1.1.0.dist-info/METADATA
xiaoranli_quiz-1.1.0.dist-info/WHEEL
xiaoranli_quiz-1.1.0.dist-info/entry_points.txt
xiaoranli_quiz-1.1.0.dist-info/top_level.txt
xiaoranli_quiz-1.1.0.dist-info/RECORD
