Metadata-Version: 2.1
Name: xiaoranli_quiz
Version: 1.1.0
Summary: A quiz application
Home-page: https://github.com/graceleeis/xiaoran-quiz
Author: xiaoranli
Author-email: 1240897116@qq.com
Classifier: Programming Language :: Python :: 3
Classifier: License :: OSI Approved :: MIT License
Classifier: Operating System :: OS Independent
Requires-Python: >=3.11
Requires-Dist: torch
Requires-Dist: prompt-toolkit
Requires-Dist: colorama
Requires-Dist: rich
Requires-Dist: RestrictedPython
Requires-Dist: jupyterlab
Requires-Dist: notebook
